{
  "DataContractVersion": "1.1",
  "DocumentTypes": [
    {
      "DocumentTypeId": "Enterprise.Accounts.Invoice",
      "Group": "Enterprise",
      "Category": "Accounts",
      "Name": "Invoice",
      "OptionalUniqueIdentifier": "myDocTypeCode",
      "TypeField": {
        "FieldId": "Enterprise.Accounts.Invoice.DocumentType",
        "FieldName": "Document Type"
      },
      "Fields": [
        {
          "FieldId": "Enterprise.Accounts.Invoice.INVOICE#",
          "FieldName": "Invoice #",
          "IsMultiValue": false,
          "Type": "Text",
          "DeriveFieldsFormat": "",
          "Components": [],
          "SetValues": [],
          "Metadata": [
            {
              "Key": "Color",
              "Value": "#038a18"
            },
            {
              "Key": "Hotkey",
              "Value": "v"
            }
          ]
        },
        {
          "FieldId": "Enterprise.Accounts.Invoice.CUSTOMERID",
          "FieldName": "CMR Id",
          "IsMultiValue": false,
          "Type": "Text",
          "DeriveFieldsFormat": "",
          "Components": [],
          "SetValues": [],
          "Metadata": [
            {
              "Key": "Color",
              "Value": "#fa6616"
            },
            {
              "Key": "Hotkey",
              "Value": "c"
            }
          ]
        },
        {
          "FieldId": "Enterprise.Accounts.Invoice.DATE",
          "FieldName": "Date",
          "IsMultiValue": false,
          "Type": "Date",
          "DeriveFieldsFormat": "year,month,day",
          "Components": [],
          "SetValues": [],
          "Metadata": [
            {
              "Key": "Color",
              "Value": "#8a97a0"
            },
            {
              "Key": "Hotkey",
              "Value": "a"
            }
          ]
        },
        {
          "FieldId": "Enterprise.Accounts.Invoice.TERMS",
          "FieldName": "Terms",
          "IsMultiValue": true,
          "Type": "Text",
          "DeriveFieldsFormat": "",
          "Components": [],
          "SetValues": [],
          "Metadata": [
            {
              "Key": "Color",
              "Value": "#6eb84a"
            },
            {
              "Key": "Hotkey",
              "Value": "e"
            }
          ]
        },
        {
          "FieldId": "Enterprise.Accounts.Invoice.ServiceFeeQty",
          "FieldName": "SF Qty",
          "IsMultiValue": false,
          "Type": "Text",
          "DeriveFieldsFormat": "",
          "Components": [],
          "SetValues": [],
          "Metadata": [
            {
              "Key": "Color",
              "Value": "#279aab"
            },
            {
              "Key": "Hotkey",
              "Value": "r"
            }
          ]
        },
        {
          "FieldId": "Enterprise.Accounts.Invoice.ServiceFeeUnitPrice",
          "FieldName": "SF UnitPrice",
          "IsMultiValue": false,
          "Type": "Text",
          "DeriveFieldsFormat": "",
          "Components": [],
          "SetValues": [],
          "Metadata": [
            {
              "Key": "Color",
              "Value": "#7252f9"
            },
            {
              "Key": "Hotkey",
              "Value": "q"
            }
          ]
        },
        {
          "FieldId": "Enterprise.Accounts.Invoice.ServiceFeeAmount",
          "FieldName": "SF Amount",
          "IsMultiValue": false,
          "Type": "Text",
          "DeriveFieldsFormat": "",
          "Components": [],
          "SetValues": [],
          "Metadata": [
            {
              "Key": "Color",
              "Value": "#b37710"
            },
            {
              "Key": "Hotkey",
              "Value": "m"
            }
          ]
        },
        {
          "FieldId": "Enterprise.Accounts.Invoice.AdditionalServicesQty",
          "FieldName": "AS Qty",
          "IsMultiValue": false,
          "Type": "Text",
          "DeriveFieldsFormat": "",
          "Components": [],
          "SetValues": [],
          "Metadata": [
            {
              "Key": "Color",
              "Value": "#5fcfb9"
            },
            {
              "Key": "Hotkey",
              "Value": "l"
            }
          ]
        },
        {
          "FieldId": "Enterprise.Accounts.Invoice.AdditionalServicesUnitPrice",
          "FieldName": "AS UnitPrice",
          "IsMultiValue": false,
          "Type": "Text",
          "DeriveFieldsFormat": "",
          "Components": [],
          "SetValues": [],
          "Metadata": [
            {
              "Key": "Color",
              "Value": "#6993d1"
            },
            {
              "Key": "Hotkey",
              "Value": "w"
            }
          ]
        },
        {
          "FieldId": "Enterprise.Accounts.Invoice.AdditionalServicesAmount",
          "FieldName": "AS Amount",
          "IsMultiValue": false,
          "Type": "Text",
          "DeriveFieldsFormat": "",
          "Components": [],
          "SetValues": [],
          "Metadata": [
            {
              "Key": "Color",
              "Value": "#e7dc5c"
            },
            {
              "Key": "Hotkey",
              "Value": "y"
            }
          ]
        },
        {
          "FieldId": "Enterprise.Accounts.Invoice.TotalAmount",
          "FieldName": "Total($)",
          "IsMultiValue": false,
          "Type": "Text",
          "DeriveFieldsFormat": "",
          "Components": [],
          "SetValues": [],
          "Metadata": [
            {
              "Key": "Color",
              "Value": "#f915c0"
            },
            {
              "Key": "Hotkey",
              "Value": "g"
            }
          ]
        },
        {
          "FieldId": "Enterprise.Accounts.Invoice.BillTo",
          "FieldName": "Bill To",
          "IsMultiValue": false,
          "Type": "Text",
          "DeriveFieldsFormat": "",
          "Components": [],
          "SetValues": [],
          "Metadata": [
            {
              "Key": "Color",
              "Value": "#15dca3"
            },
            {
              "Key": "Hotkey",
              "Value": "h"
            }
          ]
        },
        {
          "FieldId": "Enterprise.Accounts.Invoice.CoyName",
          "FieldName": "Company",
          "IsMultiValue": false,
          "Type": "Text",
          "DeriveFieldsFormat": "",
          "Components": [],
          "SetValues": [],
          "Metadata": [
            {
              "Key": "Color",
              "Value": "#da59f8"
            },
            {
              "Key": "Hotkey",
              "Value": "j"
            }
          ]
        },
        {
          "FieldId": "Enterprise.Accounts.Invoice.StAddress",
          "FieldName": "Street Address",
          "IsMultiValue": false,
          "Type": "Text",
          "DeriveFieldsFormat": "",
          "Components": [],
          "SetValues": [],
          "Metadata": [
            {
              "Key": "Color",
              "Value": "#a9ba96"
            },
            {
              "Key": "Hotkey",
              "Value": "k"
            }
          ]
        },
        {
          "FieldId": "Enterprise.Accounts.Invoice.City",
          "FieldName": "City",
          "IsMultiValue": false,
          "Type": "Text",
          "DeriveFieldsFormat": "",
          "Components": [],
          "SetValues": [],
          "Metadata": [
            {
              "Key": "Color",
              "Value": "#dc5ccc"
            },
            {
              "Key": "Hotkey",
              "Value": "z"
            }
          ]
        },
        {
          "FieldId": "Enterprise.Accounts.Invoice.PhoneNo",
          "FieldName": "Phone No",
          "IsMultiValue": false,
          "Type": "Text",
          "DeriveFieldsFormat": "",
          "Components": [],
          "SetValues": [],
          "Metadata": [
            {
              "Key": "Color",
              "Value": "#a0ba6b"
            },
            {
              "Key": "Hotkey",
              "Value": "x"
            }
          ]
        },
        {
          "FieldId": "Enterprise.Accounts.Invoice.EmailId",
          "FieldName": "Email Id",
          "IsMultiValue": false,
          "Type": "Text",
          "DeriveFieldsFormat": "",
          "Components": [],
          "SetValues": [],
          "Metadata": [
            {
              "Key": "Color",
              "Value": "#15d6e4"
            },
            {
              "Key": "Hotkey",
              "Value": "1"
            }
          ]
        },
        {
          "FieldId": "Enterprise.Accounts.Invoice.FileName",
          "FieldName": "File Name",
          "IsMultiValue": false,
          "Type": "Text",
          "DeriveFieldsFormat": "",
          "Components": [],
          "SetValues": [],
          "Metadata": [
            {
              "Key": "Color",
              "Value": "#6d22cf"
            },
            {
              "Key": "Hotkey",
              "Value": "2"
            }
          ]
        }
      ]
    },
    {
      "DocumentTypeId": "RaceAcademy.NoCategory.Invoices",
      "Group": "RaceAcademy",
      "Category": "Finance",
      "Name": "Invoices",
      "OptionalUniqueIdentifier": "",
      "TypeField": {
        "FieldId": "RaceAcademy.NoCategory.Invoices.DocumentType",
        "FieldName": "Document Type"
      },
      "Fields": [
        {
          "FieldId": "RaceAcademy.NoCategory.Invoices.BillTo",
          "FieldName": "Bill To",
          "IsMultiValue": false,
          "Type": "Text",
          "DeriveFieldsFormat": "",
          "Components": [],
          "SetValues": [],
          "Metadata": [
            {
              "Key": "Color",
              "Value": "#038a18"
            },
            {
              "Key": "Hotkey",
              "Value": "l"
            }
          ]
        },
        {
          "FieldId": "RaceAcademy.NoCategory.Invoices.SFQty",
          "FieldName": "SF Qty",
          "IsMultiValue": false,
          "Type": "Text",
          "DeriveFieldsFormat": "",
          "Components": [],
          "SetValues": [],
          "Metadata": [
            {
              "Key": "Color",
              "Value": "#fa6616"
            },
            {
              "Key": "Hotkey",
              "Value": "q"
            }
          ]
        },
        {
          "FieldId": "RaceAcademy.NoCategory.Invoices.SFUnitPrice",
          "FieldName": "SF UnitPrice",
          "IsMultiValue": false,
          "Type": "Text",
          "DeriveFieldsFormat": "",
          "Components": [],
          "SetValues": [],
          "Metadata": [
            {
              "Key": "Color",
              "Value": "#8a97a0"
            },
            {
              "Key": "Hotkey",
              "Value": "r"
            }
          ]
        },
        {
          "FieldId": "RaceAcademy.NoCategory.Invoices.SFAmount",
          "FieldName": "SF Amount",
          "IsMultiValue": false,
          "Type": "Text",
          "DeriveFieldsFormat": "",
          "Components": [],
          "SetValues": [],
          "Metadata": [
            {
              "Key": "Color",
              "Value": "#6eb84a"
            },
            {
              "Key": "Hotkey",
              "Value": "a"
            }
          ]
        },
        {
          "FieldId": "RaceAcademy.NoCategory.Invoices.ASFQty",
          "FieldName": "ASF Qty",
          "IsMultiValue": false,
          "Type": "Text",
          "DeriveFieldsFormat": "",
          "Components": [],
          "SetValues": [],
          "Metadata": [
            {
              "Key": "Color",
              "Value": "#6959f8"
            },
            {
              "Key": "Hotkey",
              "Value": "y"
            }
          ]
        },
        {
          "FieldId": "RaceAcademy.NoCategory.Invoices.ASFUnitPrice",
          "FieldName": "ASF UnitPrice",
          "IsMultiValue": false,
          "Type": "Text",
          "DeriveFieldsFormat": "",
          "Components": [],
          "SetValues": [],
          "Metadata": [
            {
              "Key": "Color",
              "Value": "#dba242"
            },
            {
              "Key": "Hotkey",
              "Value": "c"
            }
          ]
        },
        {
          "FieldId": "RaceAcademy.NoCategory.Invoices.ASFAmount",
          "FieldName": "ASF Amount",
          "IsMultiValue": false,
          "Type": "Text",
          "DeriveFieldsFormat": "",
          "Components": [],
          "SetValues": [],
          "Metadata": [
            {
              "Key": "Color",
              "Value": "#5a9afb"
            },
            {
              "Key": "Hotkey",
              "Value": "m"
            }
          ]
        },
        {
          "FieldId": "RaceAcademy.NoCategory.Invoices.Total",
          "FieldName": "Total",
          "IsMultiValue": false,
          "Type": "Text",
          "DeriveFieldsFormat": "",
          "Components": [],
          "SetValues": [],
          "Metadata": [
            {
              "Key": "Color",
              "Value": "#dfb989"
            },
            {
              "Key": "Hotkey",
              "Value": "w"
            }
          ]
        },
        {
          "FieldId": "RaceAcademy.NoCategory.Invoices.Invoice#",
          "FieldName": "Invoice#",
          "IsMultiValue": false,
          "Type": "Text",
          "DeriveFieldsFormat": "",
          "Components": [],
          "SetValues": [],
          "Metadata": [
            {
              "Key": "Color",
              "Value": "#32ad7d"
            },
            {
              "Key": "Hotkey",
              "Value": "v"
            }
          ]
        },
        {
          "FieldId": "RaceAcademy.NoCategory.Invoices.CustomerId",
          "FieldName": "Customer Id",
          "IsMultiValue": false,
          "Type": "Text",
          "DeriveFieldsFormat": "",
          "Components": [],
          "SetValues": [],
          "Metadata": [
            {
              "Key": "Color",
              "Value": "#2b42e3"
            },
            {
              "Key": "Hotkey",
              "Value": "e"
            }
          ]
        },
        {
          "FieldId": "RaceAcademy.NoCategory.Invoices.Date",
          "FieldName": "Date",
          "IsMultiValue": false,
          "Type": "Date",
          "DeriveFieldsFormat": "",
          "Components": [],
          "SetValues": [],
          "Metadata": [
            {
              "Key": "Color",
              "Value": "#67936b"
            },
            {
              "Key": "Hotkey",
              "Value": "g"
            }
          ]
        },
        {
          "FieldId": "RaceAcademy.NoCategory.Invoices.Terms",
          "FieldName": "Terms",
          "IsMultiValue": false,
          "Type": "Text",
          "DeriveFieldsFormat": "",
          "Components": [],
          "SetValues": [],
          "Metadata": [
            {
              "Key": "Color",
              "Value": "#a4aa90"
            },
            {
              "Key": "Hotkey",
              "Value": "h"
            }
          ]
        }
      ]
    }
  ],
  "Groups": [
    {
      "Name": "Enterprise",
      "Categories": [
        "Accounts"
      ]
    },
    {
      "Name": "RaceAcademy",
      "Categories": [
        "Finance"
      ]
    }
  ],
  "SupportedLanguages": [
    {
      "Name": "Undetermined Language",
      "Code": "und"
    },
    {
      "Name": "Bulgarian",
      "Code": "bul"
    },
    {
      "Name": "Cantonese",
      "Code": "yue"
    },
    {
      "Name": "Danish",
      "Code": "dan"
    },
    {
      "Name": "Dutch",
      "Code": "nld"
    },
    {
      "Name": "English",
      "Code": "eng"
    },
    {
      "Name": "French",
      "Code": "fra"
    },
    {
      "Name": "Georgian",
      "Code": "kat"
    },
    {
      "Name": "German",
      "Code": "deu"
    },
    {
      "Name": "Greek",
      "Code": "ell"
    },
    {
      "Name": "Hebrew",
      "Code": "heb"
    },
    {
      "Name": "Hindi",
      "Code": "hin"
    },
    {
      "Name": "Italian",
      "Code": "ita"
    },
    {
      "Name": "Japanese",
      "Code": "jpn"
    },
    {
      "Name": "Korean",
      "Code": "kor"
    },
    {
      "Name": "Macedonian",
      "Code": "mkd"
    },
    {
      "Name": "Mandarin",
      "Code": "zho"
    },
    {
      "Name": "Marathi",
      "Code": "mar"
    },
    {
      "Name": "Norwegian",
      "Code": "nor"
    },
    {
      "Name": "Polish",
      "Code": "pol"
    },
    {
      "Name": "Portuguese",
      "Code": "por"
    },
    {
      "Name": "Romanian",
      "Code": "ron"
    },
    {
      "Name": "Russian",
      "Code": "rus"
    },
    {
      "Name": "Serbian",
      "Code": "srp"
    },
    {
      "Name": "Spanish",
      "Code": "spa"
    },
    {
      "Name": "Swedish",
      "Code": "swe"
    },
    {
      "Name": "Telugu",
      "Code": "tel"
    }
  ]
}